.coveragerc
.gitignore
.readthedocs.yml
AUTHORS.rst
CHANGELOG.rst
CONTRIBUTING.rst
LICENSE.txt
README.rst
pyproject.toml
setup.cfg
setup.py
tox.ini
.github/workflows/release.yml
docs/Makefile
docs/authors.rst
docs/changelog.rst
docs/conf.py
docs/contributing.rst
docs/index.rst
docs/license.rst
docs/readme.rst
docs/requirements.txt
docs/_static/.gitignore
src/cpuid/__init__.py
src/cpuid/bindings.pyi
src/cpuid/cpuid_bindings.c
src/cpuid/features.py
src/cpuid/register_map.py
src/python_cpuid.egg-info/PKG-INFO
src/python_cpuid.egg-info/SOURCES.txt
src/python_cpuid.egg-info/dependency_links.txt
src/python_cpuid.egg-info/not-zip-safe
src/python_cpuid.egg-info/requires.txt
src/python_cpuid.egg-info/top_level.txt
tests/conftest.py
tests/test_register_field.py