Metadata-Version: 2.1
Name: python-cpuid
Version: 0.1.1
Summary: Call the cpuid instruction from Python.
Home-page: https://github.com/bearmetaldev/python-cpuid
Author: Olivier Desenfans
Author-email: desenfans.olivier@gmail.com
License: MIT
Project-URL: Source, https://github.com/bearmetaldev/python-cpuid
Platform: any
Classifier: Development Status :: 4 - Beta
Classifier: Programming Language :: Python
License-File: LICENSE.txt
Requires-Dist: importlib-metadata; python_version < "3.8"
Provides-Extra: testing
Requires-Dist: setuptools; extra == "testing"
Requires-Dist: pytest; extra == "testing"
Requires-Dist: pytest-cov; extra == "testing"
